txsshadmin/__init__.py
txsshadmin/cred_base.py
txsshadmin/demo.py
txsshadmin/manhole_repl.py
txsshadmin/proto_dispatcher.py
txsshadmin/service.py
txsshadmin-0.2.0.dist-info/LICENSE.txt
txsshadmin-0.2.0.dist-info/METADATA
txsshadmin-0.2.0.dist-info/WHEEL
txsshadmin-0.2.0.dist-info/top_level.txt
txsshadmin-0.2.0.dist-info/RECORD
