Metadata-Version: 2.1
Name: txsshadmin
Version: 0.2.0
Summary: Administrative SSH interface for network services.
Home-page: https://github.com/cwaldbieser/txsshadmin
Author: Carl Waldbieser
Author-email: cwaldbieser@gmail.com
License: UNKNOWN
Project-URL: Bug Reports, https://github.com/cwaldbieser/txsshadmin/issues
Project-URL: Source, https://github.com/cwaldbieser/txsshadmin
Keywords: ssh administation terminal
Platform: UNKNOWN
Classifier: Development Status :: 3 - Alpha
Classifier: Environment :: Console :: Curses
Classifier: Framework :: Twisted
Classifier: Intended Audience :: Developers
Classifier: Intended Audience :: System Administrators
Classifier: License :: OSI Approved :: GNU General Public License v3 (GPLv3)
Classifier: Programming Language :: Python :: 2
Classifier: Programming Language :: Python :: 2.7
Requires-Python: >=2.7, <3
Requires-Dist: Twisted (<20,>=17)
